oscar_odin/__init__.py
oscar_odin/apps.py
oscar_odin/exceptions.py
oscar_odin/field_resolvers.py
oscar_odin/fields.py
oscar_odin/fixtures/oscar_odin/address.json
oscar_odin/fixtures/oscar_odin/auth.json
oscar_odin/fixtures/oscar_odin/catalogue.json
oscar_odin/fixtures/oscar_odin/csv/products.csv
oscar_odin/fixtures/oscar_odin/offer.json
oscar_odin/fixtures/oscar_odin/order.json
oscar_odin/fixtures/oscar_odin/partner.json
oscar_odin/fixtures/oscar_odin/test_discount/address.json
oscar_odin/fixtures/oscar_odin/test_discount/auth.json
oscar_odin/fixtures/oscar_odin/test_discount/catalogue.json
oscar_odin/fixtures/oscar_odin/test_discount/order.json
oscar_odin/fixtures/oscar_odin/test_discount/partner.json
oscar_odin/inheritable.py
oscar_odin/mappings/__init__.py
oscar_odin/mappings/address.py
oscar_odin/mappings/auth.py
oscar_odin/mappings/catalogue.py
oscar_odin/mappings/common.py
oscar_odin/mappings/constants.py
oscar_odin/mappings/context.py
oscar_odin/mappings/helpers.py
oscar_odin/mappings/model_mapper.py
oscar_odin/mappings/order.py
oscar_odin/mappings/partner.py
oscar_odin/mappings/prefetching/__init__.py
oscar_odin/mappings/prefetching/prefetch.py
oscar_odin/mappings/prefetching/registry.py
oscar_odin/mappings/resources.py
oscar_odin/resources/__init__.py
oscar_odin/resources/address.py
oscar_odin/resources/auth.py
oscar_odin/resources/base.py
oscar_odin/resources/catalogue.py
oscar_odin/resources/order.py
oscar_odin/resources/partner.py
oscar_odin/settings.py
oscar_odin/utils.py
django_oscar_odin-0.4.0.dist-info/LICENSE
django_oscar_odin-0.4.0.dist-info/METADATA
django_oscar_odin-0.4.0.dist-info/WHEEL
django_oscar_odin-0.4.0.dist-info/RECORD
